sca3s_cli/__init__.py
sca3s_cli/cli.py
sca3s_cli/functions.py
sca3s_cli/parser.py
sca3s_cli/classes/__init__.py
sca3s_cli/classes/errors.py
sca3s_cli/classes/middleware_status.py
sca3s_cli/classes/status.py
sca3s_cli-1.0.6.dist-info/LICENSE
sca3s_cli-1.0.6.dist-info/METADATA
sca3s_cli-1.0.6.dist-info/WHEEL
sca3s_cli-1.0.6.dist-info/entry_points.txt
sca3s_cli-1.0.6.dist-info/top_level.txt
sca3s_cli-1.0.6.dist-info/zip-safe
sca3s_cli-1.0.6.dist-info/RECORD
