Metadata-Version: 2.1
Name: sca3s-cli
Version: 1.0.6
Summary: Toolkit to enable job submission to SCA3S from the command line
Home-page: https://github.com/jwsi/sca3s-cli
Author: James Webb
Author-email: james.webb@bristol.ac.uk
License: Apache2
Keywords: sca3s sca3s_cli
Classifier: Development Status :: 4 - Beta
Classifier: Intended Audience :: Developers
Classifier: License :: OSI Approved :: Apache Software License
Classifier: Operating System :: MacOS
Classifier: Operating System :: Microsoft :: Windows
Classifier: Operating System :: POSIX
Classifier: Operating System :: Unix
Classifier: Programming Language :: Python :: 3
Classifier: Topic :: Security
Classifier: Topic :: Security :: Cryptography
Classifier: Topic :: Software Development :: Libraries
License-File: LICENSE
Requires-Dist: requests (>=2.27)
Requires-Dist: rich (>=12.5.1)
